{
  "leagues": [
    {
      "id": "ebb52980-4b25-4384-bb32-26d354568f0c",
      "created_at": "2015-11-28T22:33:56-05:00",
      "updated_at": "2015-11-28T22:33:56-05:00",
      "abbreviation": "NFL",
      "color": null,
      "minutes_per_period": null,
      "name": "National Football League",
      "periods": null,
      "slug": "nfl",
      "sport": "football"
    }
  ],
  "playing_positions": [
    {
      "id": "3ce3177c-b88f-4851-9754-27dff90bcfc7",
      "created_at": "2015-11-29T22:31:28-05:00",
      "updated_at": "2015-11-29T22:31:28-05:00",
      "abbreviation": "P",
      "description": null,
      "formation": "offensive",
      "name": "Punter",
      "league_id": "ebb52980-4b25-4384-bb32-26d354568f0c"
    },
    {
      "id": "47be0cc5-0355-43d7-b16f-6efd436bb81d",
      "created_at": "2015-11-29T22:31:28-05:00",
      "updated_at": "2015-11-29T22:31:28-05:00",
      "abbreviation": "WR",
      "description": null,
      "formation": "offensive",
      "name": "Wide Receiver",
      "league_id": "ebb52980-4b25-4384-bb32-26d354568f0c"
    },
    {
      "id": "4865b69e-0361-45c6-b568-a6421f0e43df",
      "created_at": "2015-11-29T22:31:30-05:00",
      "updated_at": "2015-11-29T22:31:30-05:00",
      "abbreviation": "C",
      "description": null,
      "formation": "offensive",
      "name": "Center",
      "league_id": "ebb52980-4b25-4384-bb32-26d354568f0c"
    },
    {
      "id": "7a5d125f-5baf-4072-bfb9-93a624a61b98",
      "created_at": "2015-12-09T06:30:34-05:00",
      "updated_at": "2015-12-09T06:30:34-05:00",
      "abbreviation": "T",
      "description": null,
      "formation": "offensive",
      "name": "Tackle",
      "league_id": "ebb52980-4b25-4384-bb32-26d354568f0c"
    },
    {
      "id": "ef370948-c274-4ff7-974c-6f6224604584",
      "created_at": "2015-11-29T22:33:09-05:00",
      "updated_at": "2015-11-29T22:33:09-05:00",
      "abbreviation": "OG",
      "description": null,
      "formation": "offensive",
      "name": "Offensive Guard",
      "league_id": "ebb52980-4b25-4384-bb32-26d354568f0c"
    }
  ],
  "teams": [
    {
      "id": "5546974d-27c2-4d93-a63e-d8320952e871",
      "created_at": "2015-11-28T22:33:56-05:00",
      "updated_at": "2015-12-27T16:56:07-05:00",
      "location": "New England",
      "name": "New England",
      "nickname": "Patriots",
      "slug": "nfl-ne",
      "division_id": "7eb2130f-0d1d-4396-9595-649708fe5a6a",
      "league_id": "ebb52980-4b25-4384-bb32-26d354568f0c"
    }
  ],
  "players": [
    {
      "id": "406f822b-9364-442f-a41f-e23cabf30c88",
      "created_at": "2015-12-26T01:38:29-05:00",
      "updated_at": "2016-01-03T15:18:34-05:00",
      "active": true,
      "defensive": false,
      "first_name": "Ryan",
      "handedness": "unknown",
      "height": null,
      "unit_of_height": "inches",
      "last_name": "Allen",
      "name": "Ryan Allen",
      "offensive": true,
      "position_abbreviation": "P",
      "position_name": "Punter",
      "salary": null,
      "humanized_salary": "",
      "salary_currency": "USD",
      "school": null,
      "slug": "nfl-ryan-allen",
      "sport": "football",
      "weight": null,
      "unit_of_weight": "pounds",
      "years_of_experience": null,
      "league_id": "ebb52980-4b25-4384-bb32-26d354568f0c",
      "playing_position_id": "3ce3177c-b88f-4851-9754-27dff90bcfc7",
      "team_id": "5546974d-27c2-4d93-a63e-d8320952e871"
    },
    {
      "id": "4e11ffa4-3e82-435f-aa9d-a886e20dd6fa",
      "created_at": "2015-12-26T01:38:29-05:00",
      "updated_at": "2016-01-03T15:18:34-05:00",
      "active": true,
      "defensive": false,
      "first_name": "Danny",
      "handedness": "unknown",
      "height": null,
      "unit_of_height": "inches",
      "last_name": "Amendola",
      "name": "Danny Amendola",
      "offensive": true,
      "position_abbreviation": "WR",
      "position_name": "Wide Receiver",
      "salary": null,
      "humanized_salary": "",
      "salary_currency": "USD",
      "school": null,
      "slug": "nfl-danny-amendola",
      "sport": "football",
      "weight": null,
      "unit_of_weight": "pounds",
      "years_of_experience": null,
      "league_id": "ebb52980-4b25-4384-bb32-26d354568f0c",
      "playing_position_id": "47be0cc5-0355-43d7-b16f-6efd436bb81d",
      "team_id": "5546974d-27c2-4d93-a63e-d8320952e871"
    },
    {
      "id": "3c2e0ae8-9637-4376-b69d-c6e7cf4a7ce0",
      "created_at": "2015-12-26T01:38:38-05:00",
      "updated_at": "2015-12-28T10:39:06-05:00",
      "active": true,
      "defensive": false,
      "first_name": "David",
      "handedness": "unknown",
      "height": null,
      "unit_of_height": "inches",
      "last_name": "Andrews",
      "name": "David Andrews",
      "offensive": true,
      "position_abbreviation": "C",
      "position_name": "Center",
      "salary": null,
      "humanized_salary": "",
      "salary_currency": "USD",
      "school": null,
      "slug": "nfl-david-andrews",
      "sport": "football",
      "weight": null,
      "unit_of_weight": "pounds",
      "years_of_experience": null,
      "league_id": "ebb52980-4b25-4384-bb32-26d354568f0c",
      "playing_position_id": "4865b69e-0361-45c6-b568-a6421f0e43df",
      "team_id": "5546974d-27c2-4d93-a63e-d8320952e871"
    },
    {
      "id": "f10ee8d4-a863-4180-bb80-e605e3ecc589",
      "created_at": "2015-12-26T02:12:34-05:00",
      "updated_at": "2015-12-26T03:50:21-05:00",
      "active": false,
      "defensive": false,
      "first_name": "Mark",
      "handedness": "unknown",
      "height": 79,
      "unit_of_height": "inches",
      "last_name": "Asper",
      "name": "Mark Asper",
      "offensive": true,
      "position_abbreviation": "T",
      "position_name": "Tackle",
      "salary": 0,
      "humanized_salary": "0",
      "salary_currency": "USD",
      "school": "Oregon",
      "slug": "nfl-mark-asper",
      "sport": "football",
      "weight": 325,
      "unit_of_weight": "pounds",
      "years_of_experience": 3,
      "league_id": "ebb52980-4b25-4384-bb32-26d354568f0c",
      "playing_position_id": "7a5d125f-5baf-4072-bfb9-93a624a61b98",
      "team_id": "5546974d-27c2-4d93-a63e-d8320952e871"
    },
    {
      "id": "a2e96bc2-34db-4f5a-8f6f-8004340948d7",
      "created_at": "2015-12-26T02:00:28-05:00",
      "updated_at": "2015-12-26T02:16:58-05:00",
      "active": true,
      "defensive": false,
      "first_name": "Chris",
      "handedness": "unknown",
      "height": null,
      "unit_of_height": "inches",
      "last_name": "Barker",
      "name": "Chris Barker",
      "offensive": true,
      "position_abbreviation": "OG",
      "position_name": "Offensive Guard",
      "salary": null,
      "humanized_salary": "",
      "salary_currency": "USD",
      "school": null,
      "slug": "nfl-chris-barker",
      "sport": "football",
      "weight": null,
      "unit_of_weight": "pounds",
      "years_of_experience": null,
      "league_id": "ebb52980-4b25-4384-bb32-26d354568f0c",
      "playing_position_id": "ef370948-c274-4ff7-974c-6f6224604584",
      "team_id": "5546974d-27c2-4d93-a63e-d8320952e871"
    }
  ]
}
